sync_pre_commit_deps.py
sync_pre_commit_deps-0.0.3.dist-info/LICENSE
sync_pre_commit_deps-0.0.3.dist-info/METADATA
sync_pre_commit_deps-0.0.3.dist-info/WHEEL
sync_pre_commit_deps-0.0.3.dist-info/entry_points.txt
sync_pre_commit_deps-0.0.3.dist-info/top_level.txt
sync_pre_commit_deps-0.0.3.dist-info/RECORD
