Metadata-Version: 2.2
Name: sync_pre_commit_deps
Version: 0.0.3
Summary: Sync pre-commit hook dependencies based on other installed hooks
Home-page: https://github.com/pre-commit/sync-pre-commit-deps
Author: Max R
Author-email: maxr@outlook.com
License: MIT
Classifier: License :: OSI Approved :: MIT License
Classifier: Programming Language :: Python :: 3
Classifier: Programming Language :: Python :: 3 :: Only
Classifier: Programming Language :: Python :: Implementation :: CPython
Classifier: Programming Language :: Python :: Implementation :: PyPy
Requires-Python: >=3.9
License-File: LICENSE
Requires-Dist: ruamel.yaml>=0.17
